README
setup.py
cloudminer/__init__.py
cloudminer/cloudminer.py
cloudminer.egg-info/PKG-INFO
cloudminer.egg-info/SOURCES.txt
cloudminer.egg-info/dependency_links.txt
cloudminer.egg-info/requires.txt
cloudminer.egg-info/top_level.txt
cloudminer/tests/__init__.py
cloudminer/tests/test_filedb_cm.py
cloudminer/tests/test_iaasid_cm.py
cloudminer/tests/test_simple_cm.py