Metadata-Version: 1.0
Name: cloudminer
Version: 0.2
Summary: Persistence API for the cloudyvents API.
Home-page: http://www.nimbusproject.org/
Author: Nimbus Team
Author-email: nimbus@mcs.anl.gov
License: Apache2
Platform: UNKNOWN
